blindantspymm/__init__.py
blindantspymm/mm.py
blindantspymm-1.3.0.dist-info/LICENSE
blindantspymm-1.3.0.dist-info/METADATA
blindantspymm-1.3.0.dist-info/WHEEL
blindantspymm-1.3.0.dist-info/top_level.txt
blindantspymm-1.3.0.dist-info/RECORD
