Metadata-Version: 2.2
Name: blindantspymm
Version: 1.3.0
Summary: blind multi-channel/time-series medical image processing with antspyx
Author-email: "Avants, Tustison, Stone" <stnava@gmail.com>
License: Apache 2.0
Requires-Python: >=3.8
License-File: LICENSE
Requires-Dist: h5py>=2.10.0
Requires-Dist: numpy>=1.19.4
Requires-Dist: pandas>=1.0.1
Requires-Dist: antspyx>=0.4.2
Requires-Dist: antspynet>=0.2.8
Requires-Dist: antspyt1w>=0.9.3
Requires-Dist: antspymm
Requires-Dist: curvanato
Requires-Dist: pathlib
Requires-Dist: dipy
Requires-Dist: nibabel
Requires-Dist: scipy
Requires-Dist: siq
Requires-Dist: scikit-learn
